<?xml version="1.0" encoding="UTF-8" ?>
<ModuleList>
	<Title>Collezioni d'Arte</Title>
	<Links>
    <Link Url="Collections.aspx?name=warhol" Text="Andy Warhol Foundation" Title="Visualizza immagini"  />
    <Link Url="/ImageGroups/ImageGroups.aspx?typ=3&amp;id=1288500" Text="Ansel Adams " Title="Visualizza immagini"  />
    <Link Url="/ImageGroups/ImageGroups.aspx?typ=3&amp;id=1288501" Text="The Gallery Collection" Title="Visualizza immagini"  />
    <Link Url="/ImageGroups/ImageGroups.aspx?typ=3&amp;id=1288519" Text="Smithsonian Institution " Title="Visualizza immagini"  />
    <Link Url="/ImageGroups/ImageGroups.aspx?typ=3&amp;id=1288520" Text="SWIM Ink" Title="Visualizza immagini"  />
    <Link Url="/ImageGroups/ImageGroups.aspx?typ=3&amp;id=1288522" Text="Brett Weston Archive" Title="Visualizza immagini"  />
    <Link Url="/ImageGroups/ImageGroups.aspx?typ=3&amp;id=1288512" Text="The Picture Desk Limited" Title="Visualizza immagini"  />
    <Link Url="/ImageGroups/ImageGroups.aspx?typ=3&amp;id=1288510" Text="Historical Picture Library" Title="Visualizza immagini"  />
    <Link Url="/ImageGroups/ImageGroups.aspx?typ=3&amp;id=1288504" Text="Christie's Images" Title="Visualizza immagini"  />
    <Link Url="/ImageGroups/ImageGroups.aspx?typ=3&amp;id=1288499" Text="Fratelli Alinari" Title="Visualizza immagini"  />
    <Link Url="/ImageGroups/ImageGroups.aspx?typ=3&amp;id=1288502" Text="Blue Lantern Studio" Title="Visualizza immagini"  />
    <Link Url="/ImageGroups/ImageGroups.aspx?typ=3&amp;id=1288517" Text="Philadelphia Museum of Art" Title="Visualizza immagini"  />
    <Link Url="/ImageGroups/ImageGroups.aspx?typ=3&amp;id=1288503" Text="Brooklyn Museum" Title="Visualizza immagini"  />
    <Link Url="/ImageGroups/ImageGroups.aspx?typ=3&amp;id=1288507" Text="Fine Art Photographic Library" Title="Visualizza immagini"  />
	</Links>
</ModuleList>