<?xml version="1.0" encoding="UTF-8" ?>
<ModuleList>
	<Title>Collezioni Royalty-Free</Title>
	<Links>
    <Link Url="Collections.aspx?name=fancy" Text="Fancy" Title="Visualizza slideshow"  />
    <!--<Link Url="/ImageGroups/ImageGroups.aspx?typ=3&amp;id=" Text="Somos" Title="View images" />-->
    <Link Url="/ImageGroups/ImageGroups.aspx?typ=3&amp;id=1289158" Text="Cardinal" Title="Visualizza immagini"  />
    <Link Url="Collections.aspx?name=imagesource" Text="Image Source" Title="Visualizza slideshow"  />
    <Link Url="/ImageGroups/ImageGroups.aspx?typ=3&amp;id=1289160" Text="moodboard" Title="Visualizza immagini"  />
    <Link Url="/ImageGroups/ImageGroups.aspx?typ=3&amp;id=1289161" Text="PhotoAlto" Title="Visualizza immagini"  />
    <Link Url="/ImageGroups/ImageGroups.aspx?typ=3&amp;id=1289162" Text="Cultura" Title="Visualizza immagini"  />
    <Link Url="/ImageGroups/ImageGroups.aspx?typ=3&amp;id=1289163" Text="Juice" Title="Visualizza immagini"  />
    <Link Url="/ImageGroups/ImageGroups.aspx?typ=3&amp;id=1289165" Text="Radius" Title="Visualizza immagini"  />
    <!--<Link Url="/ImageGroups/ImageGroups.aspx?typ=3&amp;id=" Text="Clover" Title="View images" />-->
    <Link Url="/ImageGroups/ImageGroups.aspx?typ=3&amp;id=1289170" Text="ZenShui" Title="Visualizza immagini"  />
	</Links>
</ModuleList>